{
  "id": "z-stagger-silhouette",
  "name": "Z-stagger split-massing silhouette",
  "kind": "structural",
  "schema_version": "2.0",
  "skill_category": "global_silhouette",
  "description": "Overall silhouette whose footprint is two offset rectangular masses overlapping at one corner, reading as a Z (or stagger). The shift breaks up the bulk, creates a sheltered re-entrant entry corner and two outdoor terraces on opposite diagonal corners. Common in modern split-level houses and pavilions that step with a sloping site. Consumed by the global_designer to fix the envelope before space_planner subdivides the two masses.",
  "typical_dimensions": {
    "min": [
      16,
      5,
      16
    ],
    "preferred": [
      30,
      11,
      30
    ],
    "max": [
      52,
      20,
      52
    ]
  },
  "tags": {
    "category": "block",
    "style": [
      "modern",
      "minimalist",
      "fantasy"
    ]
  },
  "applicable_to": [
    "residential",
    "monument"
  ],
  "parameters": {
    "footprint_shape": "Z",
    "blocks": 2,
    "overlap_ratio": "0.2-0.4",
    "preferred_floors": "1-2",
    "entrance_side": "reentrant_corner"
  },
  "placement_rules": [
    "Footprint is two rectangles offset diagonally, overlapping at a shared corner.",
    "The overlap (20-40%) holds the shared circulation joining the two masses.",
    "The two exposed diagonal corners stay open as terraces.",
    "Each mass is >= 6 in both XZ so rooms fit.",
    "Place the entrance in the sheltered re-entrant corner."
  ],
  "style_variants": {
    "modern": {
      "palette_overrides": {
        "primary": "minecraft:smooth_quartz",
        "accent": "minecraft:smooth_stone",
        "roof": "minecraft:smooth_stone_slab",
        "trim": "minecraft:stone"
      },
      "notes": "Two white volumes sliding past each other; flat roofs, glazed re-entrant entry."
    },
    "minimalist": {
      "palette_overrides": {
        "primary": "minecraft:smooth_stone",
        "accent": "minecraft:smooth_quartz",
        "roof": "minecraft:smooth_stone_slab",
        "trim": "minecraft:polished_andesite"
      },
      "notes": "Pared-back staggered boxes; single material, sharp shadow line at the offset."
    }
  },
  "alexander_patterns_relevant": [
    "entrance-transition",
    "levels-of-scale",
    "strong-centers"
  ],
  "examples": [],
  "python_skill_signature": null
}
